README.rst
setup.py
lathe/__init__.py
lathe/checkpoint.py
lathe/cli.py
lathe/data.py
lathe/metrics.py
lathe/visual.py
lathe.egg-info/PKG-INFO
lathe.egg-info/SOURCES.txt
lathe.egg-info/dependency_links.txt
lathe.egg-info/not-zip-safe
lathe.egg-info/requires.txt
lathe.egg-info/top_level.txt